outcome/pypicloud_access_github/__init__.py
outcome/pypicloud_access_github/access.py
outcome/pypicloud_access_github/graphql/__init__.py
outcome/pypicloud_access_github/graphql/github.py
outcome/pypicloud_access_github/graphql/queries/getCurrentUser.graphql
outcome/pypicloud_access_github/graphql/queries/getOrganizationMembers.graphql
outcome/pypicloud_access_github/graphql/queries/getOrganizationPackageFiles.graphql
outcome/pypicloud_access_github/graphql/queries/getOrganizationRepositoryPermissions.graphql
outcome/pypicloud_access_github/graphql/queries/getOrganizationTeams.graphql
outcome/pypicloud_access_github/graphql/queries.py
outcome/pypicloud_access_github/graphql/schemas/__init__.py
outcome/pypicloud_access_github/graphql/schemas/models/__init__.py
outcome/pypicloud_access_github/graphql/schemas/models/connection.py
outcome/pypicloud_access_github/graphql/schemas/models/edge.py
outcome/pypicloud_access_github/graphql/schemas/models/object.py
outcome/pypicloud_access_github/graphql/schemas/models/organization.py
outcome/pypicloud_access_github/graphql/schemas/models/page_info.py
outcome/pypicloud_access_github/graphql/schemas/models/repository.py
outcome/pypicloud_access_github/graphql/schemas/models/team.py
outcome/pypicloud_access_github/graphql/schemas/models/user.py
outcome/pypicloud_access_github/graphql/schemas/queries/__init__.py
outcome/pypicloud_access_github/graphql/schemas/queries/get_current_user.py
outcome/pypicloud_access_github/graphql/schemas/queries/get_organization_members.py
outcome/pypicloud_access_github/graphql/schemas/queries/get_organization_package_files.py
outcome/pypicloud_access_github/graphql/schemas/queries/get_organization_repository_permissions.py
outcome/pypicloud_access_github/graphql/schemas/queries/get_organization_teams.py
outcome/pypicloud_access_github/poetry.py
outcome_pypicloud_access_github-1.2.9.dist-info/WHEEL
outcome_pypicloud_access_github-1.2.9.dist-info/METADATA
outcome_pypicloud_access_github-1.2.9.dist-info/RECORD
