Metadata-Version: 2.1
Name: outcome-pypicloud-access-github
Version: 1.2.9
Summary: A Github-based access backend for pypicloud.
Home-page: https://github.com/outcome-co/pypicloud-access-github-py
License: ISC
Author: Douglas Willcocks
Author-email: douglas@outcome.co
Requires-Python: >=3.8.6,<4.0.0
Classifier: License :: OSI Approved
Classifier: Programming Language :: Python :: 3
Classifier: Programming Language :: Python :: 3.9
Provides-Extra: memcache
Requires-Dist: PyGithub (>=1.54,<2.0)
Requires-Dist: gql[all] (==3.0.0.0a5)
Requires-Dist: outcome-utils (>=5.0.3,<6.0.0)
Requires-Dist: pydantic (>=1.8.1,<2.0.0)
Requires-Dist: python-memcached (>=1.59,<2.0); extra == "memcache"
Requires-Dist: toml (>=0.10.1,<0.11.0)
Project-URL: Documentation, https://github.com/outcome-co/pypicloud-access-github-py#README
Project-URL: Repository, https://github.com/outcome-co/pypicloud-access-github-py
